WorldMedia/__init__.py
WorldMedia/audio/__init__.py
WorldMedia/video/__init__.py
test/__init__.py
WorldMedia-2023.9.1.dist-info/LICENSE.txt
WorldMedia-2023.9.1.dist-info/METADATA
WorldMedia-2023.9.1.dist-info/WHEEL
WorldMedia-2023.9.1.dist-info/top_level.txt
WorldMedia-2023.9.1.dist-info/RECORD
