Metadata-Version: 2.1
Name: WorldMedia
Version: 2023.9.1
Summary: 这是一个关于多媒体的软件包
Author: anzechannel
Author-email: 348834851@qq.com
Classifier: Programming Language :: Python :: 3
Classifier: License :: OSI Approved :: MIT License
Classifier: Operating System :: OS Independent
Requires-Python: >=3.8
License-File: LICENSE.txt
